LICENSE
README.md
pdf2llm/__init__.py
pdf2llm/cli/__init__.py
pdf2llm/cli/main.py
pdf2llm/core/__init__.py
pdf2llm/core/extractor.py
pdf2llm-0.1.1.dist-info/METADATA
pdf2llm-0.1.1.dist-info/WHEEL
pdf2llm-0.1.1.dist-info/entry_points.txt
pdf2llm-0.1.1.dist-info/licenses/LICENSE
pdf2llm-0.1.1.dist-info/RECORD
