Metadata-Version: 2.4
Name: pdf2llm
Version: 0.1.1
Summary: Extract PDF content optimized for Large Language Model (LLM) consumption
Project-URL: Homepage, https://github.com/yourusername/pdf2llm
Project-URL: Bug Reports, https://github.com/yourusername/pdf2llm/issues
Project-URL: Source, https://github.com/yourusername/pdf2llm
Author-email: Your Name <your.email@example.com>
License: MIT
License-File: LICENSE
Keywords: document-processing,extraction,llm,markdown,pdf
Classifier: Development Status :: 4 - Beta
Classifier: Intended Audience :: Developers
Classifier: License :: OSI Approved :: MIT License
Classifier: Programming Language :: Python :: 3
Classifier: Programming Language :: Python :: 3.12
Classifier: Topic :: Software Development :: Libraries :: Python Modules
Classifier: Topic :: Text Processing :: Markup
Requires-Python: >=3.12
Requires-Dist: pymupdf4llm>=0.0.27
Provides-Extra: dev
Requires-Dist: black>=23.0; extra == 'dev'
Requires-Dist: pytest>=7.0; extra == 'dev'
Requires-Dist: ruff>=0.1.0; extra == 'dev'
Provides-Extra: examples
Requires-Dist: matplotlib>=3.10.5; extra == 'examples'
Requires-Dist: pillow>=11.3.0; extra == 'examples'
Requires-Dist: reportlab>=4.4.3; extra == 'examples'
